knowyourplates/__init__.py
knowyourplates/alpr.py
knowyourplates/utils.py
KnowYourPlates-0.1.1.dist-info/LICENSE
KnowYourPlates-0.1.1.dist-info/METADATA
KnowYourPlates-0.1.1.dist-info/WHEEL
KnowYourPlates-0.1.1.dist-info/top_level.txt
KnowYourPlates-0.1.1.dist-info/RECORD
