Metadata-Version: 2.1
Name: KnowYourPlates
Version: 0.1.1
Summary: Module that allows to recognize license plates from images basing on image processing algorithms.
Home-page: https://github.com/SikoraWojciech/KnowYourPlates
Author: Wojciech Sikora
Author-email: kontakt@sikorawojciech.pl
License: UNKNOWN
Platform: UNKNOWN
Classifier: Programming Language :: Python :: 3
Classifier: License :: OSI Approved :: MIT License
Classifier: Operating System :: OS Independent
Requires-Python: >=3.7
